herculens/__init__.py
herculens/info.py
herculens/Analysis/__init__.py
herculens/Analysis/plot.py
herculens/Coordinates/__init__.py
herculens/Coordinates/coord_transforms.py
herculens/Coordinates/pixel_grid.py
herculens/GenericModel/__init__.py
herculens/GenericModel/correlated_field.py
herculens/Inference/__init__.py
herculens/Inference/base_differentiable.py
herculens/Inference/loss.py
herculens/Inference/sensitivity_mapping.py
herculens/Inference/Optimization/__init__.py
herculens/Inference/Optimization/base_optim.py
herculens/Inference/Optimization/jaxopt.py
herculens/Inference/Optimization/optax.py
herculens/Inference/ProbModel/__init__.py
herculens/Inference/ProbModel/base_model.py
herculens/Inference/ProbModel/numpyro.py
herculens/Inference/Sampling/__init__.py
herculens/Inference/Sampling/base_inference.py
herculens/Inference/Sampling/sampling.py
herculens/Inference/legacy/__init__.py
herculens/Inference/legacy/base_differentiable.py
herculens/Inference/legacy/base_inference.py
herculens/Inference/legacy/covariance.py
herculens/Inference/legacy/loss.py
herculens/Inference/legacy/optimization.py
herculens/Inference/legacy/parameters.py
herculens/Inference/legacy/sampling.py
herculens/Instrument/__init__.py
herculens/Instrument/noise.py
herculens/Instrument/psf.py
herculens/LensImage/__init__.py
herculens/LensImage/lens_image.py
herculens/LensImage/lens_image_future.py
herculens/LensImage/lens_image_multiplane.py
herculens/LensImage/lensing_operator.py
herculens/LensImage/Numerics/__init__.py
herculens/LensImage/Numerics/convolution.py
herculens/LensImage/Numerics/grid.py
herculens/LensImage/Numerics/numerics.py
herculens/LightModel/__init__.py
herculens/LightModel/light_model.py
herculens/LightModel/light_model_base.py
herculens/LightModel/light_model_multiplane.py
herculens/LightModel/profile_mapping.py
herculens/LightModel/Profiles/__init__.py
herculens/LightModel/Profiles/gaussian.py
herculens/LightModel/Profiles/multipole.py
herculens-0.2.3.dist-info/licenses/AUTHORS.md
herculens-0.2.3.dist-info/licenses/LICENSE
herculens-0.2.3.dist-info/METADATA
herculens-0.2.3.dist-info/WHEEL
herculens-0.2.3.dist-info/top_level.txt
herculens-0.2.3.dist-info/RECORD
