Metadata-Version: 2.4
Name: herculens
Version: 0.2.3
Summary: Auto-differentiable strong lens modelling
Home-page: https://github.com/Herculens/herculens
Download-URL: https://github.com/Herculens/herculens/archive/refs/tags/v0.2.3.tar.gz
Author: Aymeric Galan, Austin Peel, Giorgos Vernardos & Herculens contributors
Author-email: aymeric.galan@gmail.com
License: MIT
Project-URL: Changelog, https://github.com/Herculens/herculens/blob/main/CHANGELOG.md
Keywords: herculens,lensing,gravitation,astrophysics
Requires-Python: >=3.10
License-File: LICENSE
License-File: AUTHORS.md
Requires-Dist: numpy
Requires-Dist: scipy
Requires-Dist: jax
Requires-Dist: jaxlib
Requires-Dist: objax
Requires-Dist: scikit-image
Provides-Extra: opt
Requires-Dist: matplotlib; extra == "opt"
Requires-Dist: optax; extra == "opt"
Requires-Dist: jaxopt; extra == "opt"
Requires-Dist: findiff; extra == "opt"
Requires-Dist: numpyro; extra == "opt"
Requires-Dist: blackjax; extra == "opt"
Dynamic: author
Dynamic: author-email
Dynamic: description
Dynamic: description-content-type
Dynamic: download-url
Dynamic: home-page
Dynamic: keywords
Dynamic: license
Dynamic: license-file
Dynamic: provides-extra
Dynamic: requires-dist
Dynamic: requires-python
Dynamic: summary
